MANIFEST.in
README.md
setup.cfg
setup.py
flask_fool/__init__.py
flask_fool/flask_fool.py
flask_fool.egg-info/PKG-INFO
flask_fool.egg-info/SOURCES.txt
flask_fool.egg-info/dependency_links.txt
flask_fool.egg-info/requires.txt
flask_fool.egg-info/top_level.txt
flask_fool/templates/chrome.html
flask_fool/templates/firefox.html