Metadata-Version: 1.1
Name: flask-fool
Version: 1.0.8
Summary:  A Flask extension that prevents browser access to API. 
Home-page: https://github.com/Faylixe/flask-fool
Author: Felix Voituret
Author-email: felix@voituret.fr
License: Apache Licence 2.0
Download-URL: https://github.com/Faylixe/flask-fool/archive/1.0.8.tar.gz
Keywords: flask fool
Platform: UNKNOWN
Classifier: Environment :: Web Environment
Classifier: Intended Audience :: Developers
Classifier: Operating System :: OS Independent
Classifier: Programming Language :: Python
Classifier: Topic :: Internet :: WWW/HTTP :: Dynamic Content
Classifier: Topic :: Software Development :: Libraries :: Python Modules
Classifier: Programming Language :: Python :: 2
Classifier: Programming Language :: Python :: 2.7
Classifier: Programming Language :: Python :: 3
Classifier: Programming Language :: Python :: 3.5
Classifier: Development Status :: 5 - Production/Stable
